signald/__init__.py
signald/main.py
signald/types.py
pysignald-0.1.1.dist-info/LICENSE
pysignald-0.1.1.dist-info/METADATA
pysignald-0.1.1.dist-info/WHEEL
pysignald-0.1.1.dist-info/RECORD
