Metadata-Version: 2.1
Name: pysignald
Version: 0.1.1
Summary: A library that allows communication via the Signal IM service using the signald daemon.
Home-page: https://gitlab.com/stavros/pysignald/
License: MIT
Author: Stavros Korokithakis
Author-email: hi@stavros.io
Requires-Python: >=3.5,<4.0
Classifier: License :: OSI Approved :: MIT License
Classifier: Programming Language :: Python :: 3
Classifier: Programming Language :: Python :: 3.5
Classifier: Programming Language :: Python :: 3.6
Classifier: Programming Language :: Python :: 3.7
Classifier: Programming Language :: Python :: 3.8
Classifier: Programming Language :: Python :: 3.9
Classifier: Programming Language :: Python :: 3.10
Classifier: Programming Language :: Python :: 3.11
Requires-Dist: Deprecated (>=1.2.11,<2.0.0)
Requires-Dist: attrs (>=21.2,<22.0)
Project-URL: Repository, https://gitlab.com/stavros/pysignald/
